<extension xmlns="http://ns.adobe.com/air/extension/3.1">
	<id>com.bitrhymes.appPurchase</id>
	<versionNumber>1</versionNumber>
	<platforms>
		<platform name="Android-ARM">
			<applicationDeployment>
				<nativeLibrary>InApp.jar</nativeLibrary>
				<initializer>com.bitrhymes.iab.InAppExtension</initializer>
				<finalizer>com.bitrhymes.iab.InAppExtension</finalizer>
			</applicationDeployment>
		</platform>
		<platform name="default">
			<applicationDeployment />
		</platform>
	</platforms>
</extension>